Final-Exam/Question1/Multiplier_8_8_Pipeline/pipeline_multiplier.vhd
----------------------------------------------------------------------------------
-- Company: 
-- Engineer: 
-- 
-- Create Date:    23:50:51 01/21/2022 
-- Design Name: 
-- Module Name:    pipeline_multiplier - rtl_shift_and_add 
-- Project Name: 
-- Target Devices: 
-- Tool versions: 
-- Description: 
--
-- Dependencies: 
--
-- Revision: 
-- Revision 0.01 - File Created
-- Additional Comments: 
--
----------------------------------------------------------------------------------
library ieee ;
use ieee.std_logic_1164.all;
use ieee.numeric_std.all;

entity pipeline_8x8 is
port ( 
  i_clk      : in  std_logic;
  i_rstb     : in  std_logic;
  i_ma       : in  std_logic_vector(7 downto 0);
  i_mb       : in  std_logic_vector(7 downto 0);
  o_m        : out std_logic_vector(15 downto 0));
end pipeline_8x8;

architecture pipe1 of pipeline_8x8 is

-- the architecture implements the following calculation:
-- (A[7:4] x B[3:0] + A[3:0] x B[7:4] )x2^4 + A[3:0] x B[3:0]

type p_operand is array(0 to 3) of signed(3 downto 0);
signal p_ma_hi       : p_operand; -- msb bits of the ma register
signal p_ma_lo       : p_operand; -- lsb bits of the ma register
signal p_mb_hi       : p_operand; -- msb bits of the mb register
signal p_mb_lo       : p_operand; -- lsb bits of the mb register

signal r_p1          : signed(9 downto 0);  -- 5x5 => 10 bit (8 + 2 sgn bit)
signal r_p2          : signed(8 downto 0);  -- 4x5 => 9 bit (8 + 1 sgn bit)
signal r_p3          : signed(8 downto 0);  -- 4x5 => 9 bit (8 + 1 sgn bit)
signal r_p4          : signed(7 downto 0);  -- 4x4 => 8 bit

signal r_m1          : signed(9 downto 0);  -- 5x5 => 10 bit (8 + 2 sgn bit)
signal r_m2          : signed(8 downto 0);  -- 4x5 => 9 bit (8 + 1 sgn bit)
signal r_m3          : signed(8 downto 0);  -- 4x5 => 9 bit (8 + 1 sgn bit)
signal r_m4          : signed(7 downto 0);  -- 4x4 => 8 bit

-- next two signals apply the delay of the pipeline
signal p_m1          : p_operand;
signal p_m3          : signed(3 downto 0);

begin

-- next 3 lines will be the output of m.
o_m(15 downto 8)  <= std_logic_vector(r_m4(7 downto 0));
o_m(7 downto  4)  <= std_logic_vector(p_m3);
o_m(3 downto  0)  <= std_logic_vector(p_m1(2)); -- this might need change

multiplication_steps : process(i_clk,i_rstb)
begin
    if(i_rstb='0') then
        p_ma_hi       <= (others=>(others=>'0'));
        p_ma_lo       <= (others=>(others=>'0'));
        p_mb_hi       <= (others=>(others=>'0'));
        p_mb_lo       <= (others=>(others=>'0'));
        p_m1          <= (others=>(others=>'0'));
        p_m3          <= (others=>'0');

        r_m1          <= (others=>'0');
        r_m2          <= (others=>'0');
        r_m3          <= (others=>'0');
        r_m4          <= (others=>'0');
        p_m1          <= (others=>(others=>'0'));
        p_m3          <= (others=>'0');

    elsif(rising_edge(i_clk)) then
        p_ma_hi       <= signed(i_ma(7 downto 4)) & p_ma_hi(0 to p_ma_hi'length-2);
        p_ma_lo       <= signed(i_ma(3 downto 0)) & p_ma_lo(0 to p_ma_lo'length-2);
        p_mb_hi       <= signed(i_mb(7 downto 4)) & p_mb_hi(0 to p_mb_hi'length-2);
        p_mb_lo       <= signed(i_mb(3 downto 0)) & p_mb_lo(0 to p_mb_lo'length-2);
        p_m1          <= r_m1(3 downto 0)&p_m1(0 to p_m1'length-2);
        p_m3          <= r_m3(3 downto 0);

        r_p1          <= signed('0'&p_ma_lo(0)) * signed('0'&p_mb_lo(0));
        r_p2          <= signed('0'&p_ma_lo(1)) * p_mb_hi(1);
        r_p3          <= p_ma_hi(2) * signed('0'&p_mb_lo(2)); -- this might need change
        r_p4          <= p_ma_hi(3) * p_mb_hi(3); -- this might need change

        r_m1          <= r_p1;
        r_m2          <= r_p2 + r_m1(8 downto 4);
        r_m3          <= r_p3 + r_m2;
        r_m4          <= r_p4 + r_m3(8 downto 4);
    end if;
end process multiplication_steps;

end pipe1;

Final-Exam/Question1/Multiplier_8_8_Pipeline/isim_sim_result.vcd
$date
   Sat Jan 22 16:55:09 2022
$end
$version
  P.20131013
$end
$timescale
  1ps
$end
$scope module pipeline_8x8 $end
$var wire 1 ! i_clk $end
$var wire 1 " i_rstb $end
$var wire 1 * i_ma [7] $end
$var wire 1 ) i_ma [6] $end
$var wire 1 ( i_ma [5] $end
$var wire 1 ' i_ma [4] $end
$var wire 1 & i_ma [3] $end
$var wire 1 % i_ma [2] $end
$var wire 1 $ i_ma [1] $end
$var wire 1 # i_ma [0] $end
$var wire 1 2 i_mb [7] $end
$var wire 1 1 i_mb [6] $end
$var wire 1 0 i_mb [5] $end
$var wire 1 / i_mb [4] $end
$var wire 1 . i_mb [3] $end
$var wire 1 - i_mb [2] $end
$var wire 1 , i_mb [1] $end
$var wire 1 + i_mb [0] $end
$var wire 1 B o_m [15] $end
$var wire 1 A o_m [14] $end
$var wire 1 @ o_m [13] $end
$var wire 1 ? o_m [12] $end
$var wire 1 > o_m [11] $end
$var wire 1 = o_m [10] $end
$var wire 1 < o_m [9] $end
$var wire 1 ; o_m [8] $end
$var wire 1 : o_m [7] $end
$var wire 1 9 o_m [6] $end
$var wire 1 8 o_m [5] $end
$var wire 1 7 o_m [4] $end
$var wire 1 6 o_m [3] $end
$var wire 1 5 o_m [2] $end
$var wire 1 4 o_m [1] $end
$var wire 1 3 o_m [0] $end
$var wire 1 .! r_p1 [9] $end
$var wire 1 -! r_p1 [8] $end
$var wire 1 ,! r_p1 [7] $end
$var wire 1 +! r_p1 [6] $end
$var wire 1 *! r_p1 [5] $end
$var wire 1 )! r_p1 [4] $end
$var wire 1 (! r_p1 [3] $end
$var wire 1 '! r_p1 [2] $end
$var wire 1 &! r_p1 [1] $end
$var wire 1 %! r_p1 [0] $end
$var wire 1 7! r_p2 [8] $end
$var wire 1 6! r_p2 [7] $end
$var wire 1 5! r_p2 [6] $end
$var wire 1 4! r_p2 [5] $end
$var wire 1 3! r_p2 [4] $end
$var wire 1 2! r_p2 [3] $end
$var wire 1 1! r_p2 [2] $end
$var wire 1 0! r_p2 [1] $end
$var wire 1 /! r_p2 [0] $end
$var wire 1 @! r_p3 [8] $end
$var wire 1 ?! r_p3 [7] $end
$var wire 1 >! r_p3 [6] $end
$var wire 1 =! r_p3 [5] $end
$var wire 1 <! r_p3 [4] $end
$var wire 1 ;! r_p3 [3] $end
$var wire 1 :! r_p3 [2] $end
$var wire 1 9! r_p3 [1] $end
$var wire 1 8! r_p3 [0] $end
$var wire 1 H! r_p4 [7] $end
$var wire 1 G! r_p4 [6] $end
$var wire 1 F! r_p4 [5] $end
$var wire 1 E! r_p4 [4] $end
$var wire 1 D! r_p4 [3] $end
$var wire 1 C! r_p4 [2] $end
$var wire 1 B! r_p4 [1] $end
$var wire 1 A! r_p4 [0] $end
$var wire 1 R! r_m1 [9] $end
$var wire 1 Q! r_m1 [8] $end
$var wire 1 P! r_m1 [7] $end
$var wire 1 O! r_m1 [6] $end
$var wire 1 N! r_m1 [5] $end
$var wire 1 M! r_m1 [4] $end
$var wire 1 L! r_m1 [3] $end
$var wire 1 K! r_m1 [2] $end
$var wire 1 J! r_m1 [1] $end
$var wire 1 I! r_m1 [0] $end
$var wire 1 [! r_m2 [8] $end
$var wire 1 Z! r_m2 [7] $end
$var wire 1 Y! r_m2 [6] $end
$var wire 1 X! r_m2 [5] $end
$var wire 1 W! r_m2 [4] $end
$var wire 1 V! r_m2 [3] $end
$var wire 1 U! r_m2 [2] $end
$var wire 1 T! r_m2 [1] $end
$var wire 1 S! r_m2 [0] $end
$var wire 1 d! r_m3 [8] $end
$var wire 1 c! r_m3 [7] $end
$var wire 1 b! r_m3 [6] $end
$var wire 1 a! r_m3 [5] $end
$var wire 1 `! r_m3 [4] $end
$var wire 1 _! r_m3 [3] $end
$var wire 1 ^! r_m3 [2] $end
$var wire 1 ]! r_m3 [1] $end
$var wire 1 \! r_m3 [0] $end
$var wire 1 l! r_m4 [7] $end
$var wire 1 k! r_m4 [6] $end
$var wire 1 j! r_m4 [5] $end
$var wire 1 i! r_m4 [4] $end
$var wire 1 h! r_m4 [3] $end
$var wire 1 g! r_m4 [2] $end
$var wire 1 f! r_m4 [1] $end
$var wire 1 e! r_m4 [0] $end
$var wire 1 "" p_m3 [3] $end
$var wire 1 !" p_m3 [2] $end
$var wire 1 ~! p_m3 [1] $end
$var wire 1 }! p_m3 [0] $end
$upscope $end
$enddefinitions $end
#1000000
$dumpvars
x.!
x-!
x,!
x+!
x)!
x*!
xC!
xB!
x@!
xA!
x4!
xD!
x;!
x'!
xR!
x6!
xP!
xN!
x3!
xQ!
xO!
xM!
x(!
x>!
x1!
x<!
x%!
x7!
x5!
x2!
x&!
x/!
x0!
x?!
x=!
xH!
x:!
x8!
x9!
xG!
xF!
xE!
xS!
xi!
xJ!
xT!
xa!
xW!
xc!
xh!
x\!
xg!
xL!
x`!
xK!
xb!
xl!
xk!
xe!
xV!
xX!
x[!
x_!
xd!
xU!
x^!
xI!
xf!
x]!
xZ!
xY!
xj!
11
10
1/
1-
xA
x@
0*
x?
1&
x""
1'
1+
02
0.
1,
x!"
xB
0!
x}!
1"
1)
0(
0%
1$
1#
x~!
x=
x9
x>
x6
x3
x8
x:
x;
x4
x5
x<
x7
$end
#1020000
x"
#1050000
x.!
x-!
x,!
x+!
x)!
x*!
xC!
xB!
x@!
xA!
x4!
xD!
x;!
x'!
x6!
x3!
x(!
x>!
x1!
x<!
x%!
x7!
x5!
x2!
x&!
x/!
x0!
x?!
x=!
xH!
x:!
x8!
x9!
xG!
xF!
xE!
xS!
xi!
xT!
xa!
xW!
xc!
xh!
x\!
xg!
x`!
xb!
xl!
xk!
xe!
xV!
xX!
x[!
x_!
xd!
xU!
x^!
xf!
x]!
xZ!
xY!
xj!
xA
x@
x?
xB
1!
x=
x>
x;
x<
#1100000
0!
#1150000
0.!
0-!
0,!
1+!
0)!
0*!
1'!
xR!
xP!
xN!
xQ!
xO!
xM!
1(!
1%!
0&!
xJ!
xL!
xK!
xI!
x""
x!"
1!
x}!
x~!
x9
x8
x:
x7
#1200000
0!
#1250000
04!
0R!
06!
0P!
0N!
03!
0Q!
1O!
0M!
11!
07!
15!
12!
1/!
00!
0J!
1L!
1K!
1I!
1!
#1300000
0!
#1350000
0@!
0;!
0>!
0<!
0?!
1=!
0:!
18!
19!
1S!
0T!
1W!
0V!
0X!
0[!
0U!
0Z!
1Y!
1!
#1400000
0!
#1450000
0C!
1B!
1A!
0D!
0H!
0G!
1F!
0E!
1a!
0c!
0\!
1`!
1b!
0_!
0d!
1^!
0]!
1!
x6
x3
x4
x5
#1500000
0!
#1550000
0i!
1h!
0g!
0l!
0k!
0e!
1f!
1j!
0A
1@
0?
0""
1!"
0B
1!
0}!
0~!
0=
19
1>
16
13
08
0:
0;
04
15
1<
07
